tonic/__init__.py
tonic/audio_augmentations.py
tonic/audio_transforms.py
tonic/cached_dataset.py
tonic/collation.py
tonic/dataset.py
tonic/download_utils.py
tonic/io.py
tonic/sliced_dataset.py
tonic/slicers.py
tonic/transforms.py
tonic/utils.py
tonic/datasets/__init__.py
tonic/datasets/asl_dvs.py
tonic/datasets/cifar10dvs.py
tonic/datasets/davisdataset.py
tonic/datasets/dsec.py
tonic/datasets/dvs_lips.py
tonic/datasets/dvsgesture.py
tonic/datasets/ebssa.py
tonic/datasets/hsd.py
tonic/datasets/mvsec.py
tonic/datasets/ncaltech101.py
tonic/datasets/nerdd.py
tonic/datasets/nmnist.py
tonic/datasets/ntidigits18.py
tonic/datasets/pokerdvs.py
tonic/datasets/s_mnist.py
tonic/datasets/threeET_eyetracking.py
tonic/datasets/tum_vie.py
tonic/datasets/visual_place_recognition.py
tonic/functional/__init__.py
tonic/functional/crop.py
tonic/functional/decimate.py
tonic/functional/denoise.py
tonic/functional/drop_event.py
tonic/functional/drop_pixel.py
tonic/functional/event_downsampling.py
tonic/functional/refractory_period.py
tonic/functional/spatial_jitter.py
tonic/functional/time_jitter.py
tonic/functional/time_skew.py
tonic/functional/to_averaged_timesurface.py
tonic/functional/to_bina_rep.py
tonic/functional/to_frame.py
tonic/functional/to_timesurface.py
tonic/functional/to_voxel_grid.py
tonic/functional/uniform_noise.py
tonic-1.6.0.dist-info/LICENSE.txt
tonic-1.6.0.dist-info/METADATA
tonic-1.6.0.dist-info/WHEEL
tonic-1.6.0.dist-info/pbr.json
tonic-1.6.0.dist-info/top_level.txt
tonic-1.6.0.dist-info/RECORD
