Metadata-Version: 2.1
Name: tonic
Version: 1.6.0
Summary: Neuromorphic datasets and transformations.
Home-page: UNKNOWN
Author: The Neuromorphs of Telluride
Author-email: mail@lenzgregor.com
License: GNU GPLv3
Project-URL: Source code, https://github.com/neuromorphs/tonic
Project-URL: Documentation, https://tonic.readthedocs.org
Platform: UNKNOWN
Classifier: Intended Audience :: Science/Research
Classifier: License :: OSI Approved :: GNU General Public License v3 (GPLv3)
Classifier: Programming Language :: Python :: 3
Classifier: Operating System :: OS Independent
License-File: LICENSE.txt
Requires-Dist: numpy<2.0.0
Requires-Dist: h5py
Requires-Dist: importRosbag>=1.0.4
Requires-Dist: scipy
Requires-Dist: tqdm
Requires-Dist: typing-extensions
Requires-Dist: librosa
Requires-Dist: pbr
Requires-Dist: expelliarmus
